{"unarchiveChats":false},"deviceId":"6PaK2s9MRgSj6Hopsj2o-Q","phoneId":"c9cd9321-2b2c-4b6b-8520-f19fc228e8f4","identityId":{"type":"Buffer","data":"QfX8lF/sb8Sf9HnNMfKU83JZSaU="},"registered":true,"backupToken":{"type":"Buffer","data":"GxWAbJnWsklNJdBp234qE4CZlH4="},"registration":{},"pairingCode":"ESZ8YN49","me":{"id":"967715238418:1@s.whatsapp.net","name":"خدمات                                 وتــــــــســــــــاب."},"account":{"details":"CNbPsuoBEK3unLYGGAEgACgA","accountSignatureKey":"MKC8ZljXdiaYjSkbEKaob9f6EcnKD5ackyoZ8yR1AFo=","accountSignature":"4Zk5kj0y1fdw2FkX6IgCCIna7LjAiAJkHlsqrjdCNclQTo+qu9Sf3x/tOXVIn8fFkU9SHud3n6gVUjXmWQwBAw==","deviceSignature":"wlvg4GLEo6hNJcvNgK2k4Ypp/E5u7odqE2hqDGsbM/VQh6tWG+oJXsKycwLn5eehQKYDHD4lY0Hd8OFMMQyDgA=="},"signalIdentities":[{"identifier":{"name":"967715238418:1@s.whatsapp.net","deviceId":0},"identifierKey":{"type":"Buffer","data":"BTCgvGZY13YmmI0pGxCmqG/X+hHJyg+WnJMqGfMkdQBa"}}],"platform":"smba","lastAccountSyncTimestamp":1724331824,"myAppStateKeyId":"AAAAAGrd"}
